skillcorner_tactical_on_demand/__init__.py
skillcorner_tactical_on_demand/client.py
skillcorner_tactical_on_demand/method.py
skillcorner_tactical_on_demand-0.1.0.dist-info/METADATA
skillcorner_tactical_on_demand-0.1.0.dist-info/WHEEL
skillcorner_tactical_on_demand-0.1.0.dist-info/licenses/LICENCE.md
skillcorner_tactical_on_demand-0.1.0.dist-info/RECORD
