Metadata-Version: 2.3
Name: skillcorner-tactical-on-demand
Version: 0.1.0
Summary: Python client to interact with SkillCorner Tactical API
Author-email: SkillCorner <support@skillcorner.com>
License-File: LICENCE.md
Requires-Python: <3.13,>=3.9
Requires-Dist: fitrequest>=0.8.2
